[
    {
        "brand": "Seiko",
        "brand_mask": "seiko",
        "name": "SPB143 Prospex Diver 62MAS",
        "mask": "seiko-spb143-prospex-diver-62mas",
        "image_url": "https://cdn.watchcharts.com/removebg/4bb8dabd-cd68-41ee-968e-8f30444727f0.png?d=600x600"
    },
    {
        "brand": "Seiko",
        "brand_mask": "seiko",
        "name": "SPB121 Prospex Alpinist",
        "mask": "seiko-spb121-prospex-alpinist",
        "image_url": "https://cdn.watchcharts.com/removebg/526314ec-d403-4093-9f57-bd0fa5dcd2b0.png?d=600x600"
    },
    {
        "brand": "Seiko",
        "brand_mask": "seiko",
        "name": "SSK003 5 Sports GMT",
        "mask": "seiko-ssk003-5-sports-gmt",
        "image_url": "https://cdn.watchcharts.com/removebg/f19001b5-bc70-4ec9-bc94-2c5c8ff5f231.png?d=600x600"
    },
    {
        "brand": "Seiko",
        "brand_mask": "seiko",
        "name": "SSC813 Prospex Speedtimer Solar Chronograph",
        "mask": "seiko-ssc813-prospex-speedtimer-solar-chronograph",
        "image_url": "https://cdn.watchcharts.com/removebg/73e1ec5f-7f08-4aa3-93cd-496d643af6f7.png?d=600x600"
    },
    {
        "brand": "Seiko",
        "brand_mask": "seiko",
        "name": "SPB383 Prospex",
        "mask": "seiko-spb383-prospex",
        "image_url": "https://cdn.watchcharts.com/removebg/2a8d763b-0cd3-47eb-9cd1-696ff3525537.png?d=600x600"
    },
    {
        "brand": "Seiko",
        "brand_mask": "seiko",
        "name": "SBDC191 Prospex Scuba Otani Shohei Limited Edition",
        "mask": "seiko-sbdc191-prospex-scuba-otani-shohei-limited-edition",
        "image_url": "https://cdn.watchcharts.com/removebg/fb51b293-a010-4e44-bac2-ccb9d11f3e70.png?d=600x600"
    },
    {
        "brand": "Seiko",
        "brand_mask": "seiko",
        "name": "SPB155 Prospex Alpinist",
        "mask": "seiko-spb155-prospex-alpinist",
        "image_url": "https://cdn.watchcharts.com/removebg/2af55c81-84fe-46cf-ab48-5a1981c3b7a9.png?d=600x600"
    },
    {
        "brand": "Seiko",
        "brand_mask": "seiko",
        "name": "4843-8041 Grand Quartz",
        "mask": "seiko-48438041-grand-quartz",
        "image_url": "https://cdn.watchcharts.com/removebg/d6ccf3f1-d572-488e-a0d2-fa6179f1a16b.png?d=600x600"
    },
    {
        "brand": "Seiko",
        "brand_mask": "seiko",
        "name": "SPB453 Prospex Diver Scuba 1965",
        "mask": "seiko-spb453-prospex-diver-scuba-1965",
        "image_url": "https://cdn.watchcharts.com/removebg/90409f5a-0562-4230-80d7-c8907195eb62.png?d=600x600"
    },
    {
        "brand": "Seiko",
        "brand_mask": "seiko",
        "name": "SPB455 Prospex Diver Scuba 100th Anniversary",
        "mask": "seiko-spb455-prospex-diver-scuba-100th-anniversary",
        "image_url": "https://cdn.watchcharts.com/removebg/236729f2-b6c1-4e1a-bfe6-9971b1e92e32.png?d=600x600"
    },
    {
        "brand": "Seiko",
        "brand_mask": "seiko",
        "name": "SSK021 5 Sports SKX Style",
        "mask": "seiko-ssk021-5-sports-skx-style",
        "image_url": "https://cdn.watchcharts.com/removebg/a74f5aa7-c260-4d51-a3dc-2970c63b8783.png?d=600x600"
    },
    {
        "brand": "Seiko",
        "brand_mask": "seiko",
        "name": "SLA043 Prospex Diver 62MAS 55th Anniversary Limited Edition",
        "mask": "seiko-sla043-prospex-diver-62mas-55th-anniversary-limited-edition",
        "image_url": "https://cdn.watchcharts.com/removebg/f9131843-ed76-4523-882f-20483eb4cb48.png?d=600x600"
    },
    {
        "brand": "Seiko",
        "brand_mask": "seiko",
        "name": "SARB017 Alpinist",
        "mask": "seiko-sarb017-alpinist",
        "image_url": "https://cdn.watchcharts.com/removebg/22830226-e9b3-4a85-adb3-d6d96389295c.png?d=600x600"
    },
    {
        "brand": "Seiko",
        "brand_mask": "seiko",
        "name": "SKX175 SKX",
        "mask": "seiko-skx175-skx",
        "image_url": "https://cdn.watchcharts.com/removebg/a26c777b-f951-4b9e-b8a3-688a94b62d07.png?d=600x600"
    },
    {
        "brand": "Seiko",
        "brand_mask": "seiko",
        "name": "SRPE45 Presage Cocktail Time \"Mojito\"",
        "mask": "seiko-srpe45-presage-cocktail-time-mojito",
        "image_url": "https://cdn.watchcharts.com/removebg/3d3e172b-d2b4-4475-94fa-233b474b61ac.png?d=600x600"
    },
    {
        "brand": "Seiko",
        "brand_mask": "seiko",
        "name": "SSC911 Prospex Speedtimer ‘Go Large’ Solar Chronograph",
        "mask": "seiko-ssc911-prospex-speedtimer-go-large-solar-chronograph",
        "image_url": "https://cdn.watchcharts.com/removebg/d782ae41-ac89-44cc-a936-884075eafad0.png?d=600x600"
    },
    {
        "brand": "Seiko",
        "brand_mask": "seiko",
        "name": "SPB411 Prospex Fieldmaster",
        "mask": "seiko-spb411-prospex-fieldmaster",
        "image_url": "https://cdn.watchcharts.com/removebg/6d452c22-3287-4baa-a7b3-a2331d7780ff.png?d=600x600"
    },
    {
        "brand": "Seiko",
        "brand_mask": "seiko",
        "name": "SBDY115 Prospex Save The Ocean Special Edition",
        "mask": "seiko-sbdy115-prospex-save-the-ocean-special-edition",
        "image_url": "https://cdn.watchcharts.com/removebg/99ba9b41-714d-4d5a-bfbb-52cee2ec4fb1.png?d=600x600"
    },
    {
        "brand": "Seiko",
        "brand_mask": "seiko",
        "name": "SRPK39 5 Sports Bruce Lee 55th Anniversary Limited Edition",
        "mask": "seiko-srpk39-5-sports-bruce-lee-55th-anniversary-limited-edition",
        "image_url": "https://cdn.watchcharts.com/removebg/f7c6eef9-7089-4d9e-88e5-6e031d937171.png?d=600x600"
    },
    {
        "brand": "Seiko",
        "brand_mask": "seiko",
        "name": "SRPK75 Presage Cocktail Time Star Bar Limited Edition",
        "mask": "seiko-srpk75-presage-cocktail-time-star-bar-limited-edition",
        "image_url": "https://cdn.watchcharts.com/removebg/56b5077e-40eb-44ad-b7fd-8acd20f79205.png?d=600x600"
    },
    {
        "brand": "Seiko",
        "brand_mask": "seiko",
        "name": "SSK029 5 Sports Gmt Ice Blue Limited Edition",
        "mask": "seiko-ssk029-5-sports-gmt-ice-blue-limited-edition",
        "image_url": "https://cdn.watchcharts.com/removebg/72752413-9005-4284-8739-8a17d06796bd.png?d=600x600"
    },
    {
        "brand": "Seiko",
        "brand_mask": "seiko",
        "name": "SPB317 Prospex Turtle",
        "mask": "seiko-spb317-prospex-turtle",
        "image_url": "https://cdn.watchcharts.com/removebg/9f9c33ba-ae5d-4c9d-9377-25495b2d2084.png?d=600x600"
    },
    {
        "brand": "Seiko",
        "brand_mask": "seiko",
        "name": "SPB151 Prospex Captain Willard",
        "mask": "seiko-spb151-prospex-captain-willard",
        "image_url": "https://cdn.watchcharts.com/removebg/379de15f-8fa2-4ab6-a95b-9d369866f6ee.png?d=600x600"
    },
    {
        "brand": "Seiko",
        "brand_mask": "seiko",
        "name": "SSK001 5 Sports GMT",
        "mask": "seiko-ssk001-5-sports-gmt",
        "image_url": "https://cdn.watchcharts.com/removebg/8d1b9a6b-c900-4c48-bced-0d35989553e7.png?d=600x600"
    }
]